nftpy/__init__.py
nftpy/errors.py
nftpy/EVM/__init__.py
nftpy/EVM/abi.py
nftpy/EVM/chains.py
nftpy/EVM/nft.py
nftpy/EVM/wallet.py
nftpy/Mintable/__init__.py
nftpy/Mintable/mintable.py
nftpy/OpenSea/__init__.py
nftpy/OpenSea/collection.py
nftpy/OpenSea/opensea.py
nftpy/OpenSea/wallet.py
nftpy/Rarible/__init__.py
nftpy/Rarible/collection.py
nftpy/Rarible/rarible.py
nftpy/Rarible/wallet.py
nftpy-1.2.1.dist-info/LICENSE
nftpy-1.2.1.dist-info/METADATA
nftpy-1.2.1.dist-info/WHEEL
nftpy-1.2.1.dist-info/RECORD
