Metadata-Version: 2.1
Name: nftpy
Version: 1.2.1
Summary: A NFT specific Python library for easy NFT integration in Python
Home-page: https://github.com/coulterstutz/nftpy
License: MIT
Author: CoulterStutz
Author-email: coultercash@gmail.com
Requires-Python: >=3.9,<4.0
Classifier: License :: OSI Approved :: MIT License
Classifier: Programming Language :: Python :: 3
Classifier: Programming Language :: Python :: 3.9
Classifier: Programming Language :: Python :: 3.10
Classifier: Programming Language :: Python :: 3.11
Classifier: Programming Language :: Python :: 3.12
Requires-Dist: requests (>=2.28.1,<3.0.0)
Requires-Dist: web3 (>=6.2.0,<7.0.0)
Project-URL: Repository, https://github.com/coulterstutz/nftpy
